{
  "main": {
    "id": "923afe895bc0fb96",
    "type": "split",
    "children": [
      {
        "id": "4c06bd57015e6c08",
        "type": "tabs",
        "children": [
          {
            "id": "62373ef63dc65329",
            "type": "leaf",
            "state": {
              "type": "empty",
              "state": {},
              "icon": "lucide-file",
              "title": "New tab"
            }
          }
        ]
      }
    ],
    "direction": "vertical"
  },
  "left": {
    "id": "1384ad5738ba12e0",
    "type": "split",
    "children": [
      {
        "id": "b012c0e4ae86e155",
        "type": "tabs",
        "children": [
          {
            "id": "7a8ebf8d785a20d2",
            "type": "leaf",
            "state": {
              "type": "file-explorer",
              "state": {
                "sortOrder": "alphabetical",
                "autoReveal": false
              },
              "icon": "lucide-folder-closed",
              "title": "Files"
            }
          },
          {
            "id": "bc1f7fe85513ab71",
            "type": "leaf",
            "state": {
              "type": "search",
              "state": {
                "query": "",
                "matchingCase": false,
                "explainSearch": false,
                "collapseAll": false,
                "extraContext": false,
                "sortOrder": "alphabetical"
              },
              "icon": "lucide-search",
              "title": "Search"
            }
          },
          {
            "id": "cd97f27bf5a42fc6",
            "type": "leaf",
            "state": {
              "type": "bookmarks",
              "state": {},
              "icon": "lucide-bookmark",
              "title": "Bookmarks"
            }
          }
        ]
      }
    ],
    "direction": "horizontal",
    "width": 559.5
  },
  "right": {
    "id": "0b65d3ec2cc046ea",
    "type": "split",
    "children": [
      {
        "id": "b5b97882dc96b8c4",
        "type": "tabs",
        "children": [
          {
            "id": "e7f28c3b73e7362d",
            "type": "leaf",
            "state": {
              "type": "backlink",
              "state": {
                "collapseAll": false,
                "extraContext": false,
                "sortOrder": "alphabetical",
                "showSearch": false,
                "searchQuery": "",
                "backlinkCollapsed": false,
                "unlinkedCollapsed": true
              },
              "icon": "links-coming-in",
              "title": "Backlinks"
            }
          },
          {
            "id": "bf08e5778992c519",
            "type": "leaf",
            "state": {
              "type": "outgoing-link",
              "state": {
                "linksCollapsed": false,
                "unlinkedCollapsed": true
              },
              "icon": "links-going-out",
              "title": "Outgoing links"
            }
          },
          {
            "id": "1ba032c9ed51c780",
            "type": "leaf",
            "state": {
              "type": "tag",
              "state": {
                "sortOrder": "frequency",
                "useHierarchy": true,
                "showSearch": false,
                "searchQuery": ""
              },
              "icon": "lucide-tags",
              "title": "Tags"
            }
          },
          {
            "id": "efe3278f6600fb98",
            "type": "leaf",
            "state": {
              "type": "outline",
              "state": {
                "followCursor": false,
                "showSearch": false,
                "searchQuery": ""
              },
              "icon": "lucide-list",
              "title": "Outline"
            }
          }
        ]
      }
    ],
    "direction": "horizontal",
    "width": 300,
    "collapsed": true
  },
  "left-ribbon": {
    "hiddenItems": {
      "switcher:Open quick switcher": false,
      "graph:Open graph view": false,
      "canvas:Create new canvas": false,
      "daily-notes:Open today's daily note": false,
      "templates:Insert template": false,
      "command-palette:Open command palette": false,
      "bases:Create new base": false
    }
  },
  "active": "62373ef63dc65329",
  "lastOpenFiles": [
    "Cloud & Infra/Fault Tolerance.md",
    "Cloud & Infra/Debt Log.md",
    "Lybralis/PosgreSql/Untitled.md",
    "Cloud & Infra/Deployment strategies.md",
    "ტერმინები/Batching Vs Streaming.md",
    "ტერმინები/Streaming.md",
    "Network/RPC (Remote Procedure Call).md",
    "ტერმინები/Interceptors.md",
    "ტერმინები/Connection Resiliency.md",
    "Tools/RabbitMQ/RPC Pattern.md",
    "Tools/RabbitMQ",
    "PNGS/Pasted image 20251027102716.png",
    "PNGS/Pasted image 20251027102629.png",
    "PNGS/Pasted image 20251027102600.png",
    "PNGS/Pasted image 20251027102534.png",
    "Pasted image 20251025221515.png",
    "Solutions/დისტრიბუციული ქეში მექანიზმები.md",
    "PDF/1761030962892.pdf",
    "PDF",
    "New folder",
    "PNGS/Pasted image 20251025221515.png",
    "PNGS/Pasted image 20251025224010.png",
    "PNGS/Pasted image 20251025223911.png",
    "PNGS/Pasted image 20251025223813.png",
    "PNGS/Pasted image 20251025223740.png",
    "ტერმინები/Atomic Operation.md",
    "PNGS",
    "ტერმინები/Idempotent Operation.md",
    "ტერმინები/stateful session object.md",
    "1761030962892.pdf",
    "Lybralis/EF Core/concurrency handling.md",
    "Lybralis/EF Core/DbContext Pooling.md",
    "README.md",
    "დისტრიბუციული ქეში მექანიზმები.md",
    "Dictionary.md",
    "Index Optimization.md",
    "Lybralis.md",
    "Unconfirmed 886022.crdownload",
    "Lybralis/EF Core/transactional consistency vs. partial commit.md",
    "Lybralis/EF Core/EF-ის resilient executor.md",
    "Lybralis/EF Core/Compiled Queries.md",
    "Lybralis/EF Core/Value Conversions.md",
    "ტერმინები/Retention.md",
    "Lybralis/EF Core/Index Optimization",
    "ტერმინები/Programming Concepts",
    "Lybralis/PosgreSql",
    "Untitled.canvas"
  ]
}